metaapi_cloud_metastats_sdk/__init__.py
metaapi_cloud_metastats_sdk/metastats.py
metaapi_cloud_metastats_sdk/models.py
metaapi_cloud_metastats_sdk/clients/__init__.py
metaapi_cloud_metastats_sdk/clients/domain_client.py
metaapi_cloud_metastats_sdk/clients/domain_client_test.py
metaapi_cloud_metastats_sdk/clients/error_handler.py
metaapi_cloud_metastats_sdk/clients/http_client.py
metaapi_cloud_metastats_sdk/clients/http_client_test.py
metaapi_cloud_metastats_sdk/clients/metastats_client.py
metaapi_cloud_metastats_sdk/clients/metastats_client_test.py
metaapi_cloud_metastats_sdk/clients/metastats_models.py
metaapi_cloud_metastats_sdk/clients/timeout_exception.py
metaapi_cloud_metastats_sdk-5.1.0.dist-info/LICENSE
metaapi_cloud_metastats_sdk-5.1.0.dist-info/METADATA
metaapi_cloud_metastats_sdk-5.1.0.dist-info/WHEEL
metaapi_cloud_metastats_sdk-5.1.0.dist-info/top_level.txt
metaapi_cloud_metastats_sdk-5.1.0.dist-info/RECORD
